{
  "id": 119,
  "questions": [
    {
      "id": 39,
      "question": "Under each heading, please tick the ONE box that best describes your health TODAY:",
      "type": "CHOICE",
      "order": 1,
      "answers": [
        {
          "id": 36,
          "value": "I have no problems walking about"
        },
        {
          "id": 37,
          "value": "I have some problems walking about"
        },
        {
          "id": 38,
          "value": "I have a lot of problems walking about"
        }
      ],
      "defaultAnswer": null,
      "multiple": false,
      "container": null
    },
    {
      "id": 43,
      "question": "Looking after myself, please tick the ONE box that best describes your health TODAY:",
      "type": "CHOICE",
      "order": 2,
      "answers": [
        {
          "id": 40,
          "value": "I have no problems washing or dressing myself"
        },
        {
          "id": 41,
          "value": "I have some problems washing or dressing myself"
        },
        {
          "id": 42,
          "value": "I have a lot of problems washing or dressing myself"
        }
      ],
      "defaultAnswer": null,
      "multiple": false,
      "container": null
    },
    {
      "id": 47,
      "question": "Doing usual activities please tick the ONE box that best describes your health TODAY (for example, work, study, housework, family or leisure activities):",
      "type": "CHOICE",
      "order": 3,
      "answers": [
        {
          "id": 44,
          "value": "I have no problems doing my usual activities"
        },
        {
          "id": 45,
          "value": "I have some problems doing my usual activities"
        },
        {
          "id": 46,
          "value": "I have a lot of problems doing my usual activities"
        }
      ],
      "defaultAnswer": null,
      "multiple": false,
      "container": null
    },
    {
      "id": 51,
      "question": "Having pain/ discomfort:",
      "type": "CHOICE",
      "order": 4,
      "answers": [
        {
          "id": 48,
          "value": "I have no pain or discomfort"
        },
        {
          "id": 49,
          "value": "I have some pain or discomfort"
        },
        {
          "id": 50,
          "value": "I have a lot of pain or discomfort"
        }
      ],
      "defaultAnswer": null,
      "multiple": false,
      "container": null
    },
    {
      "id": 55,
      "question": "Feeling worried, sad or unhappy:",
      "type": "CHOICE",
      "order": 5,
      "answers": [
        {
          "id": 52,
          "value": "I am not worried, sad or unhappy"
        },
        {
          "id": 53,
          "value": "I am a bit worried, sad or unhappy"
        },
        {
          "id": 54,
          "value": "I am very worries, sad or unhappy"
        }
      ],
      "defaultAnswer": null,
      "multiple": false,
      "container": null
    },
    {
      "id": 61,
      "question": "How often do you feel lonely?",
      "type": "CHOICE",
      "order": 6,
      "answers": [
        {
          "id": 56,
          "value": "Often / always"
        },
        {
          "id": 57,
          "value": "Some of the time"
        },
        {
          "id": 58,
          "value": "Occasionally"
        },
        {
          "id": 59,
          "value": "Hardly ever"
        },
        {
          "id": 60,
          "value": "Never"
        }
      ],
      "defaultAnswer": null,
      "multiple": false,
      "container": null
    },
    {
      "id": 67,
      "question": "How would you rate your general health TODAY:",
      "type": "CHOICE",
      "order": 7,
      "answers": [
        {
          "id": 62,
          "value": "Excellent"
        },
        {
          "id": 63,
          "value": "Very good"
        },
        {
          "id": 64,
          "value": "Good"
        },
        {
          "id": 65,
          "value": "Fair"
        },
        {
          "id": 66,
          "value": "Poor"
        }
      ],
      "defaultAnswer": null,
      "multiple": false,
      "container": null
    },
    {
      "id": 68,
      "question": "Do you think you currently have/ had a COVID-19 infection?",
      "type": "BOOL",
      "order": 8,
      "defaultAnswer": null,
      "container": null
    },
    {
      "id": 69,
      "question": "Have you been tested for a COVID-19 infection?",
      "type": "BOOL",
      "order": 9,
      "defaultAnswer": null,
      "container": null
    },
    {
      "id": 72,
      "question": "Have you been hospitalised for a COVID-19 infection?",
      "type": "BOOL",
      "order": 10,
      "defaultAnswer": null,
      "container": {
        "subQuestions": [
          {
            "id": 70,
            "question": "How many days were you sick?",
            "type": "TEXT",
            "order": 1,
            "multiline": false,
            "container": null
          }
        ],
        "boolDependsOn": true
      }
    },
    {
      "id": 83,
      "question": "To what degree have you experienced the following symptoms in the last 7 days:",
      "type": "TITLE",
      "order": 11,
      "container": {
        "subQuestions": [
          {
            "id": 73,
            "question": "Headache",
            "type": "BOOL",
            "order": 1,
            "defaultAnswer": null,
            "container": null
          },
          {
            "id": 74,
            "question": "Muscle pain/aches",
            "type": "BOOL",
            "order": 2,
            "defaultAnswer": null,
            "container": null
          },
          {
            "id": 75,
            "question": "Difficulty breathing",
            "type": "BOOL",
            "order": 3,
            "defaultAnswer": null,
            "container": null
          },
          {
            "id": 76,
            "question": "Fever/ high temperature",
            "type": "BOOL",
            "order": 4,
            "defaultAnswer": null,
            "container": null
          },
          {
            "id": 77,
            "question": "Sore throat",
            "type": "BOOL",
            "order": 5,
            "defaultAnswer": null,
            "container": null
          },
          {
            "id": 78,
            "question": "Dry cough",
            "type": "BOOL",
            "order": 6,
            "defaultAnswer": null,
            "container": null
          },
          {
            "id": 79,
            "question": "Wet cough",
            "type": "BOOL",
            "order": 7,
            "defaultAnswer": null,
            "container": null
          },
          {
            "id": 80,
            "question": "I felt physically exhausted",
            "type": "BOOL",
            "order": 8,
            "defaultAnswer": null,
            "container": null
          },
          {
            "id": 81,
            "question": "loss of smell and taste",
            "type": "BOOL",
            "order": 9,
            "defaultAnswer": null,
            "container": null
          }
        ]
      }
    },
    {
      "id": 84,
      "question": "How much have you been concerned about the corona crisis in the past 7 days?",
      "type": "RANGE",
      "order": 12,
      "minValue": 1,
      "maxValue": 10,
      "minText": "Not concerned",
      "maxText": "Extremely concerned",
      "defaultValue": null,
      "container": null
    },
    {
      "id": 85,
      "question": "How would you rate your quality of life over the last 7 days?",
      "type": "RANGE",
      "order": 13,
      "minValue": 1,
      "maxValue": 10,
      "minText": "Terrible",
      "maxText": "Outstanding",
      "defaultValue": null,
      "container": null
    },
    {
      "id": 86,
      "question": "How socially isolated have you felt in the last 7 days?",
      "type": "RANGE",
      "order": 14,
      "minValue": 1,
      "maxValue": 10,
      "minText": "Not socially isolated",
      "maxText": "Extremely socially isolated",
      "defaultValue": null,
      "container": null
    },
    {
      "id": 87,
      "question": "If you suffer from depression, how much has this condition been affected by the COVID-19 crisis in the last 7 days?",
      "type": "RANGE",
      "order": 15,
      "minValue": 1,
      "maxValue": 10,
      "minText": "Not at all",
      "maxText": "Extremely depressed",
      "defaultValue": null,
      "container": null
    },
    {
      "id": 88,
      "question": "If you suffer from anxiety, how much has this condition been affected by the COVID-19 crisis in the last 7 days?",
      "type": "RANGE",
      "order": 16,
      "minValue": 1,
      "maxValue": 10,
      "minText": "Not at all",
      "maxText": "Extremely anxious",
      "defaultValue": null,
      "container": null
    },
    {
      "id": 94,
      "question": "How would you rate your overall mental health?",
      "type": "CHOICE",
      "order": 17,
      "answers": [
        {
          "id": 89,
          "value": "Excellent"
        },
        {
          "id": 90,
          "value": "Very good"
        },
        {
          "id": 91,
          "value": "Good"
        },
        {
          "id": 92,
          "value": "Fair"
        },
        {
          "id": 93,
          "value": "Poor"
        }
      ],
      "defaultAnswer": null,
      "multiple": false,
      "container": null
    },
    {
      "id": 95,
      "question": "Has the COVID-19 crisis affected the way you normally source your food/ medicines?",
      "type": "BOOL",
      "order": 18,
      "defaultAnswer": null,
      "container": null
    },
    {
      "id": 100,
      "question": "Where do you currently shop for your groceries?",
      "type": "CHOICE",
      "order": 19,
      "answers": [
        {
          "id": 96,
          "value": "Local supermarket"
        },
        {
          "id": 97,
          "value": "Online shopping"
        },
        {
          "id": 98,
          "value": "Local corner shops"
        },
        {
          "id": 99,
          "value": "Farmer’s market"
        }
      ],
      "defaultAnswer": null,
      "multiple": false,
      "container": null
    },
    {
      "id": 104,
      "question": "How healthy is your eating pattern compared to the period before the COVID-19 crisis?",
      "type": "CHOICE",
      "order": 20,
      "answers": [
        {
          "id": 101,
          "value": "Much less healthy"
        },
        {
          "id": 102,
          "value": "Just as healthy"
        },
        {
          "id": 103,
          "value": "Healthier"
        }
      ],
      "defaultAnswer": null,
      "multiple": false,
      "container": null
    },
    {
      "id": 110,
      "question": "How would you rate your overall diet?",
      "type": "CHOICE",
      "order": 21,
      "answers": [
        {
          "id": 105,
          "value": "Excellent"
        },
        {
          "id": 106,
          "value": "Very good"
        },
        {
          "id": 107,
          "value": "Good"
        },
        {
          "id": 108,
          "value": "Fair"
        },
        {
          "id": 109,
          "value": "Poor"
        }
      ],
      "defaultAnswer": null,
      "multiple": false,
      "container": null
    },
    {
      "id": 114,
      "question": "How many hours of moderately intense exercise did you do before the Covid-19 crisis?",
      "type": "CHOICE",
      "order": 22,
      "answers": [
        {
          "id": 111,
          "value": "Less than 1 hour"
        },
        {
          "id": 112,
          "value": "1-2 hours"
        },
        {
          "id": 113,
          "value": "More than 2 hours"
        }
      ],
      "defaultAnswer": null,
      "multiple": false,
      "container": null
    },
    {
      "id": 117,
      "question": "Has the COVID-19 crisis affected your ability to exercise?",
      "type": "BOOL",
      "order": 23,
      "defaultAnswer": null,
      "container": {
        "subQuestions": [
          {
            "id": 115,
            "question": "If yes, how?",
            "type": "TEXT",
            "order": 1,
            "multiline": false,
            "container": null
          }
        ],
        "boolDependsOn": true
      }
    },
    {
      "id": 118,
      "question": "Has the COVID-19 crisis changed the way that you use social media?",
      "type": "TEXT",
      "order": 24,
      "multiline": true,
      "container": null
    }
  ],
  "nameId": "REGULAR",
  "description": null,
  "version": 0
}